{
  "common": {
    "button": {
      "search": "Search",
      "cancel": "Cancel",
      "delete": "Delete",
      "save": "Save",
      "login": "Login",
      "register": "Register",
      "stay": "Stays",
      "flights": "Flights",
      "car": "Car Rentals",
      "attract": "Attractions",
      "taxi": "Airport taxis",
      "wherein": "Where are you going",
      "adult": "adult",
      "children": "childrent",
      "room": "room",
      "howtob": "How to Book",
      "contactus": "Contact Us",
      "helpcenter": "Help Center",
      "careers": "Careers",
      "aboutus": "About Us",
      "product": "Products",
      "hotel": "Hotels",
      "flightH": "Flight and Hotel",
      "experience": "Experience",
      "airportT": "Airport Transport",
      "carR": "Car Rental",
      "villas": "Villas",
      "apartments": "Apartments",
      "other": "Other",
      "bookingA": "Booking Affiliate",
      "blog": "Blog",
      "privacy": "Privacy Notice",
      "termC": "Termc and Conditions",
      "registerE": "Register Your Eccommodation",
      "registerA": "Register Your Accommodation",
      "trending": "Trending destinations",
      "saveTM": "Save time, save money!",
      "attractlove": "Suggested location",
      "canB": "can be done through",
      "payby": "You can pay by",
      "lifeT": "A lifetime of discounts? It's Genius.",
      "claimR": " Get rewarded for your travels. Unlock instant savings of 10% or more with a free Booking account"
    }
  }
}
